{
  "stats": {
    "suites": 1,
    "tests": 1,
    "passes": 0,
    "pending": 0,
    "failures": 1,
    "start": "2022-11-19T18:52:09.619Z",
    "end": "2022-11-19T18:52:17.199Z",
    "duration": 7580
  },
  "tests": [
    {
      "title": "Checks for all the elements in installation page",
      "fullTitle": "test elements assertions Checks for all the elements in installation page",
      "duration": 5966,
      "currentRetry": 0,
      "err": {
        "message": "The following error originated from your application code, not from Cypress. It was caused by an unhandled promise rejection.\n\n  > 3000ms timeout exceeded\n\nWhen Cypress detects uncaught errors originating from your application it will automatically fail the current test.\n\nThis behavior is configurable, and you can choose to turn this off by listening to the `uncaught:exception` event.\n\nhttps://on.cypress.io/uncaught-exception-from-application\n\nBecause this error occurred during a `before each` hook we are skipping the remaining tests in the current suite: `test elements assertions`",
        "name": "Error",
        "stack": "Error: The following error originated from your application code, not from Cypress. It was caused by an unhandled promise rejection.\n\n  > 3000ms timeout exceeded\n\nWhen Cypress detects uncaught errors originating from your application it will automatically fail the current test.\n\nThis behavior is configurable, and you can choose to turn this off by listening to the `uncaught:exception` event.\n\nhttps://on.cypress.io/uncaught-exception-from-application\n\nBecause this error occurred during a `before each` hook we are skipping the remaining tests in the current suite: `test elements assertions`\n    at <unknown> (https://docs.nativebase.io/_next/static/chunks/90-fef73f5fabb3bca1.js:1:1478928)\n    at i (https://docs.nativebase.io/installation:1:1454)\n    at <unknown> (https://docs.nativebase.io/installation:1:1827)",
        "parsedStack": [
          {
            "message": "Error: The following error originated from your application code, not from Cypress. It was caused by an unhandled promise rejection.",
            "whitespace": ""
          },
          {
            "message": "",
            "whitespace": ""
          },
          {
            "message": "> 3000ms timeout exceeded",
            "whitespace": "  "
          },
          {
            "message": "",
            "whitespace": ""
          },
          {
            "message": "When Cypress detects uncaught errors originating from your application it will automatically fail the current test.",
            "whitespace": ""
          },
          {
            "message": "",
            "whitespace": ""
          },
          {
            "message": "This behavior is configurable, and you can choose to turn this off by listening to the `uncaught:exception` event.",
            "whitespace": ""
          },
          {
            "message": "",
            "whitespace": ""
          },
          {
            "message": "https://on.cypress.io/uncaught-exception-from-application",
            "whitespace": ""
          },
          {
            "function": "<unknown>",
            "fileUrl": "https://docs.nativebase.io/_next/static/chunks/90-fef73f5fabb3bca1.js",
            "originalFile": "https://docs.nativebase.io/_next/static/chunks/90-fef73f5fabb3bca1.js",
            "line": 1,
            "column": 1478928,
            "whitespace": "    "
          },
          {
            "function": "i",
            "fileUrl": "https://docs.nativebase.io/installation",
            "originalFile": "https://docs.nativebase.io/installation",
            "line": 1,
            "column": 1454,
            "whitespace": "    "
          },
          {
            "function": "<unknown>",
            "fileUrl": "https://docs.nativebase.io/installation",
            "originalFile": "https://docs.nativebase.io/installation",
            "line": 1,
            "column": 1827,
            "whitespace": "    "
          }
        ]
      }
    }
  ],
  "pending": [],
  "failures": [
    {
      "title": "\"before each\" hook for \"Checks for all the elements in installation page\"",
      "fullTitle": "test elements assertions \"before each\" hook for \"Checks for all the elements in installation page\"",
      "currentRetry": 0,
      "err": {
        "message": "The following error originated from your application code, not from Cypress. It was caused by an unhandled promise rejection.\n\n  > 3000ms timeout exceeded\n\nWhen Cypress detects uncaught errors originating from your application it will automatically fail the current test.\n\nThis behavior is configurable, and you can choose to turn this off by listening to the `uncaught:exception` event.\n\nhttps://on.cypress.io/uncaught-exception-from-application\n\nBecause this error occurred during a `before each` hook we are skipping the remaining tests in the current suite: `test elements assertions`",
        "name": "Error",
        "stack": "Error: The following error originated from your application code, not from Cypress. It was caused by an unhandled promise rejection.\n\n  > 3000ms timeout exceeded\n\nWhen Cypress detects uncaught errors originating from your application it will automatically fail the current test.\n\nThis behavior is configurable, and you can choose to turn this off by listening to the `uncaught:exception` event.\n\nhttps://on.cypress.io/uncaught-exception-from-application\n\nBecause this error occurred during a `before each` hook we are skipping the remaining tests in the current suite: `test elements assertions`\n    at <unknown> (https://docs.nativebase.io/_next/static/chunks/90-fef73f5fabb3bca1.js:1:1478928)\n    at i (https://docs.nativebase.io/installation:1:1454)\n    at <unknown> (https://docs.nativebase.io/installation:1:1827)",
        "parsedStack": [
          {
            "message": "Error: The following error originated from your application code, not from Cypress. It was caused by an unhandled promise rejection.",
            "whitespace": ""
          },
          {
            "message": "",
            "whitespace": ""
          },
          {
            "message": "> 3000ms timeout exceeded",
            "whitespace": "  "
          },
          {
            "message": "",
            "whitespace": ""
          },
          {
            "message": "When Cypress detects uncaught errors originating from your application it will automatically fail the current test.",
            "whitespace": ""
          },
          {
            "message": "",
            "whitespace": ""
          },
          {
            "message": "This behavior is configurable, and you can choose to turn this off by listening to the `uncaught:exception` event.",
            "whitespace": ""
          },
          {
            "message": "",
            "whitespace": ""
          },
          {
            "message": "https://on.cypress.io/uncaught-exception-from-application",
            "whitespace": ""
          },
          {
            "function": "<unknown>",
            "fileUrl": "https://docs.nativebase.io/_next/static/chunks/90-fef73f5fabb3bca1.js",
            "originalFile": "https://docs.nativebase.io/_next/static/chunks/90-fef73f5fabb3bca1.js",
            "line": 1,
            "column": 1478928,
            "whitespace": "    "
          },
          {
            "function": "i",
            "fileUrl": "https://docs.nativebase.io/installation",
            "originalFile": "https://docs.nativebase.io/installation",
            "line": 1,
            "column": 1454,
            "whitespace": "    "
          },
          {
            "function": "<unknown>",
            "fileUrl": "https://docs.nativebase.io/installation",
            "originalFile": "https://docs.nativebase.io/installation",
            "line": 1,
            "column": 1827,
            "whitespace": "    "
          }
        ]
      }
    }
  ],
  "passes": []
}